{
    "rules" :[
        {
            "entity" : "business",
            "objectname" : "Account",
            "operation" : "upsert",
            "externalid" : "Oracle_CRM_External_ID__c",
            "batchsize" : "50",
            "fixedmapping" : {
                "recordtypeid" : "0120h000000iA7uAAE",
                "Billing_Entity__c" : "PR",
                "Oracle_Migrated__c" : "true",
                "vlocity_cmt__Status__c" : "Active",
                "vlocity_cmt__vCustomerPriority__c" : "Medium",
                "VerificationStatus__c" : "Verified",
                "vlocity_cmt__Active__c" : "Yes",
                "vlocity_cmt__CreditScore__c" : 800,
                "forseva1__Credit_Review_Date__c" : "2023-07-07",
                "vlocity_cmt__CreditRating__c" : "A",
                "vlocity_cmt__PreferredLanguage__c" : "English",
                "vlocity_cmt__contactpreferences__c" : "eMail",
                "PR_IsMobileCustomer__c" : "true"
            },
            "mapping" : {
                "cust_prnt_id": "Oracle_CRM_External_ID__c",
                "currencyisocode": "CurrencyIsoCode",
                "vlocity_cmt__vCustomerPriority__c" : "vlocity_cmt__vCustomerPriority__c",
                "Oracle_Migrated__c" : "Oracle_Migrated__c",
                "name": "Name",
                "vlocity_cmt__accountpaymenttype__c": "vlocity_cmt__AccountPaymentType__c",
                "phone": "Phone",
                "cw_account_type__c": "CW_Account_Type__c",
                "type": "Type",
                "customer_type__c" : "Customer_Type__c",
                "customer_sub_type__c" : "Customer_Sub_Type__c",
                "billingcity": "BillingCity",
                "billingcountry": "BillingCountry",
                "billingstate": "BillingState",
                "billingstreet": "BillingStreet",
                "billingpostalcode": "BillingPostalCode",
                "countryaccount__c": "CountryAccount__c",
                "bp_country__c":"BP_Country__c",
                "employee_range__c": "Employee_Range__c",
                "recordtypeid": "RecordTypeId",
                "shippingcity": "ShippingCity",
                "shippingcountry": "ShippingCountry",
                "shippingstate": "ShippingState",
                "shippingstreet": "ShippingStreet",
                "shippingpostalcode": "ShippingPostalCode",
                "vlocity_cmt__Status__c": "vlocity_cmt__Status__c",
                "pr_customer_number__c" : "PR_Customer_Number__c",
                "vlocity_cmt__taxid__c": "NIT_Tax_Number__c",
                "Billing_Entity__c" : "Billing_Entity__c",
                "VerificationStatus__c" : "VerificationStatus__c",
                "industry" : "Industry",
                "pr_consumerpinnumber__c" : "PR_ConsumerPINNumber__c",
                "vlocity_cmt__Active__c":"vlocity_cmt__Active__c",
                "vlocity_cmt__CreditScore__c" : "vlocity_cmt__CreditScore__c",
                "vlocity_cmt__CreditRating__c": "vlocity_cmt__CreditRating__c",
                "vlocity_cmt__PreferredLanguage__c" : "vlocity_cmt__PreferredLanguage__c",
                "vlocity_cmt__contactpreferences__c" : "vlocity_cmt__ContactPreferences__c",
                "IdOwner" : "OwnerId",
                "forseva1__Credit_Review_Date__c" : "forseva1__Credit_Review_Date__c",
                "PR_IsMobileCustomer__c" : "PR_IsMobileCustomer__c",
                "FAN_Number__c" : "FAN_Number__c",
                "vlocity_cmt__taxexemptiontype__c" : "vlocity_cmt__TaxExemptionType__c",
                "vlocity_cmt__taxexemptionenddate__c" : "vlocity_cmt__TaxExemptionEndDate__c",
                "prb2b_taxexemptionreasoncode__c" : "PRB2B_TaxExemptionReasonCode__c",
                "prb2b_taxcertificatenumber__c" : "PRB2B_TaxCertificateNumber__c"
            },
            "postmapping" : {
                "id" : "Id",
                "Oracle_CRM_External_ID__c" : "cust_prnt_id",
                "success" : "Success",
                "created" : "Created",
                "errors" : "Errors",
                "OwnerId" : "OwnerId",
                "recordtypeid" : "RecordTypeId"
            }
        },
        {
            "entity" : "billing",
            "objectname" : "Account",
            "operation" : "upsert",
            "externalid" : "Oracle_CRM_External_ID__c",
            "batchsize" : "50",
            "fixedmapping" : {
                "recordtypeid" : "0120h000000iA7sAAE",
                "Billing_Entity__c" : "PR",
                "vlocity_cmt__Active__c" : "yes",
                "Oracle_Migrated__c" : "true",  
                "vlocity_cmt__PreferredLanguage__c" : "English",
                "VerificationStatus__c" : "Verified",
                "vlocity_cmt__Status__c" : "Active",
                "PR_IsMobileCustomer__c" : "true",
                "RecordTypeName__c" : "Billing"
            },
            "mapping": {
                "pr_customer_number__c": "Oracle_CRM_External_ID__c",
                "vlocity_cmt__PreferredLanguage__c" : "vlocity_cmt__PreferredLanguage__c",
                "Oracle_Migrated__c" : "Oracle_Migrated__c",
                "prcustomernumber" : "PR_Customer_Number__c",
                "Id" : "ParentId",
                "currencyisocode": "CurrencyIsoCode",
                "type" : "Type",
                "cw_account_type__c" : "CW_Account_Type__c",
                "name": "Name",
                "vlocity_cmt__accountpaymenttype__c": "vlocity_cmt__AccountPaymentType__c",
                "phone": "Phone",
                "billingcity": "BillingCity",
                "billingcountry": "BillingCountry",
                "billingstate": "BillingState",
                "billingstreet": "BillingStreet",
                "billingpostalcode": "BillingPostalCode",
                "bp_country__c":"BP_Country__c",
                "country_of_origin__c": "CountryAccount__c",
                "customer_type__c" : "Customer_Type__c",
                "vlocity_cmt__taxid__c" : "NIT_Tax_Number__c",
                "recordtypeid": "RecordTypeId",
                "shippingcity": "ShippingCity",
                "shippingcountry": "ShippingCountry",
                "shippingstate": "ShippingState",
                "shippingstreet": "ShippingStreet",
                "shippingpostalcode": "ShippingPostalCode",
                "Billing_Entity__c" : "Billing_Entity__c",
                "vlocity_cmt__Status__c": "vlocity_cmt__Status__c",
                "VerificationStatus__c" : "VerificationStatus__c",
                "vlocity_cmt__contactpreferences__c" : "vlocity_cmt__ContactPreferences__c",
                "vlocity_cmt__RootAccountId__c":"vlocity_cmt__RootAccountId__c",
                "vlocity_cmt__Active__c":"vlocity_cmt__Active__c",
                "vlocity_cmt__billdeliverymethod__c": "vlocity_cmt__BillDeliveryMethod__c",
                "ssp_autopayenable__c" : "SSP_AutopayEnable__c",
                "pr_cycleday__c" : "PR_CycleDay__c",
                "billing_outstanding_balance__c":"Billing_Outstanding_Balance__c",
                "vlocity_cmt__billcycle__c" : "vlocity_cmt__BillCycle__c",
                "pr_email__c":"PR_Email__c",
                "OwnerId" : "OwnerId",
                "PR_IsMobileCustomer__c" : "PR_IsMobileCustomer__c",
                "FAN_Number__c" : "FAN_Number__c",
                "RecordTypeName__c" : "RecordTypeName__c"
            },
            "postmapping" : {
                "id" : "Id",
                "Oracle_CRM_External_ID__c" : "Oracle_CRM_External_ID__c",
                "ParentId" : "ParentId",
                "success" : "Success",
                "created" : "Created",
                "errors" : "Errors",
                "OwnerId" : "OwnerId",
                "recordtypeid" : "RecordTypeId",
                "FAN_Number__c" : "FAN_Number__c" 
            }
        },
        {
            "entity" : "service",
            "objectname" : "Account",
            "operation" : "upsert",
            "externalid" : "Oracle_CRM_External_ID__c",
            "batchsize" : "50",
            "fixedmapping" : {
                "recordtypeid" : "0120h000000iA7yAAE",
                "Billing_Entity__c" : "PR",
                "vlocity_cmt__Active__c" : "Yes",
                "vlocity_cmt__Status__c" : "Active"
            },
            "mapping": {
                "pr_customer_number__c": "Oracle_CRM_External_ID__c",
                "Id" : "ParentId",
                "currencyisocode": "CurrencyIsoCode",
                "cw_account_type__c" : "CW_Account_Type__c",
                "name": "Name",
                "vlocity_cmt__accountpaymenttype__c": "vlocity_cmt__AccountPaymentType__c",
                "phone": "Phone",
                "billingcity": "BillingCity",
                "billingcountry": "BillingCountry",
                "billingstate": "BillingState",
                "billingstreet": "BillingStreet",
                "billingpostalcode": "BillingPostalCode",
                "bp_country__c":"BP_Country__c",
                "customer_type__c" : "Customer_Type__c",
                "vlocity_cmt__taxid__c" :  "vlocity_cmt__TaxId__c",
                "recordtypeid": "RecordTypeId",
                "segment__c":"Segment__c",
                "shippingcity": "ShippingCity",
                "shippingcountry": "ShippingCountry",
                "shippingstate": "ShippingState",
                "shippingstreet": "ShippingStreet",
                "shippingpostalcode": "ShippingPostalCode",
                "Billing_Entity__c" : "Billing_Entity__c",
                "vlocity_cmt__contactpreferences__c" : "vlocity_cmt__ContactPreferences__c",
                "vlocity_cmt__RootAccountId__c":"vlocity_cmt__RootAccountId__c",
                "vlocity_cmt__Status__c" : "vlocity_cmt__Status__c",
                "vlocity_cmt__Active__c":"vlocity_cmt__Active__c",
                "FAN_Number__c" : "FAN_Number__c"
            },
            "postmapping" : {
                "id" : "Id",
                "Oracle_CRM_External_ID__c" : "PR_Customer_Number__c",
                "success" : "Success",
                "created" : "Created",
                "errors" : "Errors",
                "recordtypeid" : "RecordTypeId"
            }
        },
        {
            "entity" : "contact",
            "objectname" : "Contact",
            "operation" : "upsert",
            "externalid" : "Oracle_CRM_External_ID__c",
            "batchsize" : "50",
            "fixedmapping" : {
                "recordtypeid" : "012300000000wzaAAA",
                "Oracle_Migrated__c" : "true",
                "Billing_Entity__c" : "PR",
                "Temp_PIN__c" : "1234",
                "Verification_Status__c" : "Verified"
            },
            "mapping":{
                "recordtypeid": "RecordTypeId",
                "vlocity_cmt__isactive__c": "vlocity_cmt__IsActive__c",
                "vlocity_cmt__authorized__c": "vlocity_cmt__Authorized__c",
                "currencyisocode": "CurrencyIsoCode",
                "businessaccountid": "AccountId",
                "individualid":"IndividualId",
                "contact_id" : "Oracle_CRM_External_ID__c",
                "job_category__c": "Job_Category__c",
                "title" : "Title",
                "Verification_Status__c" : "Verification_Status__c",
                "vlocity_cmt__contactnumber__c": "vlocity_cmt__ContactNumber__c",
                "phone": "Phone",
                "department": "Department",
                "documenttype__c": "DocumentType__c",
                "firstname": "FirstName",
                "homephone": "HomePhone",
                "ismigrated__c": "IsMigrated__c",
                "vlocity_cmt__ispersonaccount__c": "vlocity_cmt__IsPersonAccount__c",
                "lastname": "LastName",
                "mailingcity": "MailingCity",
                "mailingcountry": "MailingCountry",
                "email": "Email",
                "hasoptedoutofemail": "HasOptedOutOfEmail",
                "contact_type__c": "Contact_Type__c",
                "mailingstate": "MailingState",
                "mailingstreet": "MailingStreet",
                "mailingpostalcode": "MailingPostalCode",
                "mobilephone": "MobilePhone",
                "vlocity_cmt__middlename__c" : "vlocity_cmt__MiddleName__c",
                "Oracle_Migrated__c" : "Oracle_Migrated__c",
                "OwnerId" : "OwnerId",
                "vlocity_cmt__isprimary__c" : "PR_Is_Primary_Authorized_Contact__c"
            },
            "postmapping" : {
                "id" : "Id",
                "Oracle_CRM_External_ID__c" : "contact_id",
                "AccountId" : "AccountId",
                "IndividualId" : "IndividualId",
                "success" : "Success",
                "created" : "Created",
                "errors" : "Errors"
            }

        },
        {
            "entity" : "paymentmethod",
            "objectname" : "vlocity_cmt__PaymentMethod__c",
            "operation" : "insert",
            "externalid" : "",
            "batchsize" : "50",
            "fixedmapping" : {
                "CurrencyIsoCode" : "USD"

            },
            "mapping" : {
                "billingid": "vlocity_cmt__AccountId__c",
                "vlocity_cmt__isactive__c" : "vlocity_cmt__IsActive__c",
                "vlocity_cmt__paymentcustomeridentifier__c" : "vlocity_cmt__PaymentCustomerIdentifier__c",
                "vlocity_cmt__methodtype__c" : "vlocity_cmt__MethodType__c",
                "vlocity_cmt__routingtransitnumber__c" : "vlocity_cmt__RoutingTransitNumber__c",
                "external_payment_method_type__c" : "External_Payment_Method_Type__c",
                "vlocity_cmt__isprimary__c" : "vlocity_cmt__IsPrimary__c",
                "vlocity_cmt__expirationmonth__c":"vlocity_cmt__ExpirationMonth__c",
                "vlocity_cmt__expirationyear__c":"vlocity_cmt__ExpirationYear__c"
            },
            "postmapping" : {
                "id" : "Id",
                "vlocity_cmt__PaymentCustomerIdentifier__c" : "vlocity_cmt__paymentcustomeridentifier__c",
                "success" : "Success",
                "created" : "Created",
                "errors" : "Errors"
            }
        },
        {
            "entity" : "individual",
            "objectname" : "Individual",
            "operation" : "insert",
            "externalid" : "",
            "batchsize" : "100",
            "fixedmapping" : {
                "CurrencyIsoCode" : "USD"
            },
            "mapping" : {
                "firstname" : "FirstName",
                "lastname" : "LastName"
            },
            "postmapping" : {
                "id" : "Id",
                "cust_prnt_id" : "cust_prnt_id",
                "individual_id" : "individual_id",
                "success" : "Success",
                "created" : "Created",
                "errors" : "Errors"
            }
        },
        {
            "entity" : "consent",
            "objectname" : "ContactPointTypeConsent",
            "operation" : "insert",
            "externalid" : "",
            "batchsize" : "50",
            "fixedmapping" : {
                "CurrencyIsoCode" : "USD"
            },
            "mapping" : {
                "partyid" : "PartyId",
                "ContactPointType" : "ContactPointType",
                "Name" : "Name",
                "PrivacyConsentStatus" : "PrivacyConsentStatus"
            },
            "postmapping" : {
                "id" : "Id",
                "party_id" : "party_id",
                "success" : "Success",
                "created" : "Created",
                "errors" : "Errors"
            }
        },
        {
            "entity" : "contract",
            "objectname" : "Contract",
            "operation" : "insert",
            "externalid" : "Contract_Number__c",
            "batchsize" : "50",
            "fixedmapping" : {
                "CurrencyIsoCode" : "USD"
            },
            "mapping" : {
                "contrct_id":"Contract_Number__c",
                "contrct_start_dt":"StartDate",
                "contrct_type_cd":"vlocity_cmt__ContractType__c",
                "vlocity_cmt__terminatedate__c":"vlocity_cmt__TerminateDate__c",
                "contrct_lngth_dur":"ContractTerm",
                "agr_sts_cd":"Contract_Type__c",
                "order_id":"Order_Number__c",
                "MasterOrder" : "vlocity_cmt__OrderId__c",
                "business_id" : "AccountId"
            },
            "postmapping" : {
                "id" : "Id",
                "contrct_id" : "contrct_id",
                "success" : "Success",
                "created" : "Created",
                "errors" : "Errors"
            }
        }
    ]
}